python_project_minify/__init__.py
python_project_minify/__main__.py
python_project_minify/ignore.py
python_project_minify/python_project_minify.py
python_project_minify-1.0.1.dist-info/LICENSE
python_project_minify-1.0.1.dist-info/METADATA
python_project_minify-1.0.1.dist-info/WHEEL
python_project_minify-1.0.1.dist-info/entry_points.txt
python_project_minify-1.0.1.dist-info/top_level.txt
python_project_minify-1.0.1.dist-info/RECORD
