Metadata-Version: 2.1
Name: python-project-minify
Version: 1.0.1
Summary: A quick way to compile your Python project into it's most compact form. Built on the great python-minify package.
Home-page: https://github.com/w-kuipers/python-project-minify
Author: Wibo Kuipers
Author-email: w.kuipers@filmage.nl
Project-URL: Bug Tracker, https://github.com/w-kuipers/python-project-minify/issues
Classifier: Programming Language :: Python :: 3
Classifier: License :: OSI Approved :: MIT License
Classifier: Operating System :: OS Independent
Requires-Python: >=3.6
License-File: LICENSE
Requires-Dist: python-minifier ==2.9.0
Requires-Dist: tqdm ==4.66.1
Requires-Dist: colorama ==0.4.6
